easytag.py
icm_django_easytag-1.0.1.dist-info/LICENSE.txt
icm_django_easytag-1.0.1.dist-info/METADATA
icm_django_easytag-1.0.1.dist-info/RECORD
icm_django_easytag-1.0.1.dist-info/WHEEL
icm_django_easytag-1.0.1.dist-info/top_level.txt
