Metadata-Version: 2.1
Name: icm-django-easytag
Version: 1.0.1
Summary: A generic class to facilitate the creation of complex template tags.
Home-page: https://github.com/icmanage/django-easytag
Author: Autumn Valenta
Author-email: tvalenta@pivotalenergysolutions.com
License: UNKNOWN
Download-URL: https://github.com/icmanage/django-easytag/archive/1.0.1.tar.gz
Keywords: django bootstrap
Platform: UNKNOWN
Classifier: Development Status :: 5 - Production/Stable
Classifier: Environment :: Web Environment
Classifier: Framework :: Django
Classifier: License :: OSI Approved :: Apache Software License
Classifier: Programming Language :: Python :: 2
Classifier: Programming Language :: Python :: 2.7
Classifier: Topic :: Internet :: WWW/HTTP
Classifier: Topic :: Internet :: WWW/HTTP :: Dynamic Content
Classifier: Topic :: Software Development :: Libraries :: Python Modules
Requires-Dist: django (<2.0,>=1.7)
